imdb/__init__.py
imdb/imdb.py
tdm_castle-0.0.1.dist-info/LICENSE
tdm_castle-0.0.1.dist-info/METADATA
tdm_castle-0.0.1.dist-info/WHEEL
tdm_castle-0.0.1.dist-info/top_level.txt
tdm_castle-0.0.1.dist-info/RECORD
