Metadata-Version: 2.1
Name: tdm-castle
Version: 0.0.1
Summary: Python library to fulfill Purdue Data Mine Project 09 requirements.
Author-email: Bryce Castle <castle5@purdue.edu>
License: MIT License        
Keywords: example,imdb,tutorial,FILL IN
Classifier: License :: OSI Approved :: MIT License
Classifier: Programming Language :: Python
Classifier: Programming Language :: Python :: 3
Requires-Python: >=3.10
License-File: LICENSE
Requires-Dist: lxml (>=4.9.1)
Requires-Dist: requests (>=2.28.1)
